all_libs/A1.txt
all_libs/A2.txt
all_libs/A3.txt
all_libs/A4.txt
all_libs/B1.txt
all_libs/B2.txt
all_libs/B4.txt
all_libs/B6.txt
all_libs/B7.txt
all_libs/DL.txt
all_libs/__init__.py
yagamiioits-0.1.0.dist-info/LICENSE
yagamiioits-0.1.0.dist-info/METADATA
yagamiioits-0.1.0.dist-info/WHEEL
yagamiioits-0.1.0.dist-info/top_level.txt
yagamiioits-0.1.0.dist-info/RECORD
