Metadata-Version: 2.1
Name: yagamiioits
Version: 0.1.0
Summary: A sample package that includes text files
Home-page: https://github.com/yourusername/yagamiioits
Author: Temp Name
Author-email: temp.email@example.com
Classifier: Programming Language :: Python :: 3
Classifier: License :: OSI Approved :: MIT License
Classifier: Operating System :: OS Independent
Requires-Python: >=3.6
License-File: LICENSE
